post_tracker/__init__.py
post_tracker/__main__.py
post_tracker/app.py
post_tracker/cli_utils.py
post_tracker/custom_types.py
post_tracker/errors.py
post_tracker/logger.py
post_tracker/main.py
post_tracker/utils.py
post_tracker-0.3.1.dist-info/METADATA
post_tracker-0.3.1.dist-info/WHEEL
post_tracker-0.3.1.dist-info/entry_points.txt
post_tracker-0.3.1.dist-info/licenses/LICENSE
post_tracker-0.3.1.dist-info/RECORD
