Metadata-Version: 2.3
Name: post-tracker
Version: 0.3.1
Summary: this is a command line tool to get tracking information about your parcels from tracking.post.ir
Project-URL: Repository, https://github.com/AmirAref/post-tracker
Project-URL: Homepage, https://github.com/AmirAref/post-tracker
Author-email: Amir Aref <amiraref808@gmail.com>
License-Expression: MIT
License-File: LICENSE
Classifier: Development Status :: 4 - Beta
Classifier: Framework :: AsyncIO
Classifier: Framework :: Pydantic
Classifier: Framework :: Pydantic :: 2
Classifier: Operating System :: POSIX
Classifier: Programming Language :: Python
Classifier: Programming Language :: Python :: 3
Requires-Python: >=3.9
Requires-Dist: bs4>=0.0.2
Requires-Dist: httpx>=0.27.0
Requires-Dist: pydantic>=2.8.2
Requires-Dist: rich>=13.8.0
Requires-Dist: user-agent>=0.1.10
